pyproject_parser/__init__.py
pyproject_parser/__main__.py
pyproject_parser/classes.py
pyproject_parser/parsers.py
pyproject_parser/py.typed
pyproject_parser/type_hints.py
pyproject_parser/utils.py
pyproject_parser/cli/__init__.py
pyproject_parser/cli/_json_encoders.py
pyproject_parser-0.14.0.dist-info/METADATA
pyproject_parser-0.14.0.dist-info/WHEEL
pyproject_parser-0.14.0.dist-info/entry_points.txt
pyproject_parser-0.14.0.dist-info/licenses/LICENSE
pyproject_parser-0.14.0.dist-info/RECORD
