Metadata-Version: 2.4
Name: pyproject-parser
Version: 0.14.0
Summary: Parser for 'pyproject.toml'
Project-URL: Homepage, https://github.com/repo-helper/pyproject-parser
Project-URL: Issue Tracker, https://github.com/repo-helper/pyproject-parser/issues
Project-URL: Source Code, https://github.com/repo-helper/pyproject-parser
Project-URL: Documentation, https://pyproject-parser.readthedocs.io/en/latest
Author-email: Dominic Davis-Foster <dominic@davis-foster.co.uk>
License: Copyright (c) 2021 Dominic Davis-Foster
License-File: LICENSE
Keywords: metadata,packaging,pep518,pep621,pyproject,toml
Classifier: Development Status :: 4 - Beta
Classifier: Intended Audience :: Developers
Classifier: License :: OSI Approved :: MIT License
Classifier: Operating System :: OS Independent
Classifier: Programming Language :: Python
Classifier: Programming Language :: Python :: 3 :: Only
Classifier: Programming Language :: Python :: 3.7
Classifier: Programming Language :: Python :: 3.8
Classifier: Programming Language :: Python :: 3.9
Classifier: Programming Language :: Python :: 3.10
Classifier: Programming Language :: Python :: 3.11
Classifier: Programming Language :: Python :: 3.12
Classifier: Programming Language :: Python :: 3.13
Classifier: Programming Language :: Python :: Implementation :: CPython
Classifier: Programming Language :: Python :: Implementation :: PyPy
Classifier: Topic :: Software Development :: Libraries :: Python Modules
Classifier: Topic :: System :: Archiving :: Packaging
Classifier: Typing :: Typed
Requires-Python: >=3.7
Requires-Dist: apeye-core>=1.0.0
Requires-Dist: attrs>=20.3.0
Requires-Dist: dom-toml>=2.0.0
Requires-Dist: domdf-python-tools>=2.8.0
Requires-Dist: license-expression>=30.0.0
Requires-Dist: natsort>=7.1.1
Requires-Dist: packaging>=20.9
Requires-Dist: shippinglabel>=1.0.0
Requires-Dist: typing-extensions!=4.7.0,>=3.7.4.3
Provides-Extra: all
Requires-Dist: click>=7.1.2; extra == 'all'
Requires-Dist: consolekit>=1.4.1; extra == 'all'
Requires-Dist: docutils<0.22,>=0.16; extra == 'all'
Requires-Dist: readme-renderer[md]>=27.0; extra == 'all'
Requires-Dist: sdjson>=0.3.1; extra == 'all'
Provides-Extra: cli
Requires-Dist: click>=7.1.2; extra == 'cli'
Requires-Dist: consolekit>=1.4.1; extra == 'cli'
Requires-Dist: sdjson>=0.3.1; extra == 'cli'
Provides-Extra: readme
Requires-Dist: docutils<0.22,>=0.16; extra == 'readme'
Requires-Dist: readme-renderer[md]>=27.0; extra == 'readme'
